devtorch/__init__.py
devtorch/crossval.py
devtorch/evaluation.py
devtorch/model.py
devtorch/query.py
devtorch/train.py
devtorch/util.py
tests/__init__.py
tests/test_model.py
tests/test_train.py
devtorch-0.0.7.dist-info/LICENSE.md
devtorch-0.0.7.dist-info/METADATA
devtorch-0.0.7.dist-info/WHEEL
devtorch-0.0.7.dist-info/top_level.txt
devtorch-0.0.7.dist-info/RECORD
